Metadata-Version: 1.0
Name: featurengineering
Version: 1.0
Summary: Package for EDA and featurengineering
Home-page: UNKNOWN
Author: Moustafa Ashraf
Author-email: mosafehashf@gmail.com
License: UNKNOWN
Platform: UNKNOWN
